itk_parabolicmorphology-1.3.1.dist-info/entry_points.txt
itk_parabolicmorphology-1.3.1.dist-info/WHEEL
itk_parabolicmorphology-1.3.1.dist-info/RECORD
itk_parabolicmorphology-1.3.1.dist-info/METADATA
itk_parabolicmorphology-1.3.1.dist-info/licenses/LICENSE
itk/ParabolicMorphologyPython.py
itk/itkMorphologicalSharpeningImageFilterPython.py
itk/_ParabolicMorphologyPython.so
itk/itkParabolicOpenImageFilterPython.py
itk/itkParabolicErodeImageFilterPython.py
itk/itkParabolicDilateImageFilterPython.py
itk/itkParabolicCloseImageFilterPython.py
itk/itkMorphologicalSignedDistanceTransformImageFilterPython.py
itk/itkMorphologicalDistanceTransformImageFilterPython.py
itk/Configuration/ParabolicMorphologyConfig.py
itk/Configuration/ParabolicMorphology_snake_case.py
itk_parabolicmorphology.libs/libtbb-3c88584c.so.12.9
